{
    "source": "http://forums.goha.ru/showthread.php?t=150619",
    "languages": ["en", "ru"],
    "native_language": "en",
    "templates": { "male": {"probability": 1,
                            "genders": ["m"],
                            "template": ["prefix", "male_suffix"]},
                   "male_with_connection": {"probability": 1,
                                            "genders": ["m"],
                                            "template": ["prefix", "connection" ,"male_suffix"]},
                   "female": {"probability": 1,
                              "genders": ["f"],
                              "template": ["prefix", "female_suffix"]},
                   "female_with_connection": {"probability": 1,
                                              "genders": ["f"],
                                              "template": ["prefix", "connection", "female_suffix"]}
                 },

    "tables": { "prefix": [{"languages": {"en": "Aed", "ru":"Аэд"}},
                           {"languages": {"en": "Ael", "ru":"Аэль"}},
                           {"languages": {"en": "Aelf", "ru":"Аэльф"}},
                           {"languages": {"en": "Aen", "ru":"Аэн"}},
                           {"languages": {"en": "Aeth", "ru":"Аэт"}},
                           {"languages": {"en": "Alth", "ru":"Альт"}},
                           {"languages": {"en": "An", "ru":"Ан"}},
                           {"languages": {"en": "And", "ru":"Анд"}},
                           {"languages": {"en": "Ar", "ru":"Ар"}},
                           {"languages": {"en": "Arg", "ru":"Арг"}},
                           {"languages": {"en": "Ast", "ru":"Аст"}},
                           {"languages": {"en": "Ath", "ru":"Ат"}},
                           {"languages": {"en": "Av", "ru":"Ав"}},
                           {"languages": {"en": "Ban", "ru":"Бан"}},
                           {"languages": {"en": "Bel", "ru":"Бель"}},
                           {"languages": {"en": "Beth", "ru":"Бет"}},
                           {"languages": {"en": "Cad", "ru":"Кад"}},
                           {"languages": {"en": "Cael", "ru":"Каэль"}},
                           {"languages": {"en": "Caem", "ru":"Каэм"}},
                           {"languages": {"en": "Caeth", "ru":"Каэт"}},
                           {"languages": {"en": "Cal", "ru":"Каль"}},
                           {"languages": {"en": "Cam", "ru":"Кам"}},
                           {"languages": {"en": "Cel", "ru":"Кэль"}},
                           {"languages": {"en": "Cir", "ru":"Кир"}},
                           {"languages": {"en": "El", "ru":"Эль"}},
                           {"languages": {"en": "Eld", "ru":"Элд"}},
                           {"languages": {"en": "Elth", "ru":"Эльт"}},
                           {"languages": {"en": "En", "ru":"Эн"}},
                           {"languages": {"en": "End", "ru":"Энд"}},
                           {"languages": {"en": "Er", "ru":"Эр"}},
                           {"languages": {"en": "Ers", "ru":"Эрс"}},
                           {"languages": {"en": "Fand", "ru":"Фенд"}},
                           {"languages": {"en": "Fer", "ru":"Фер"}},
                           {"languages": {"en": "Ferg", "ru":"Ферг"}},
                           {"languages": {"en": "Fim", "ru":"Фим"}},
                           {"languages": {"en": "Fin", "ru":"Фин"}},
                           {"languages": {"en": "Gal", "ru":"Гал"}},
                           {"languages": {"en": "Gald", "ru":"Галд"}},
                           {"languages": {"en": "Gaen", "ru":"Гаэн"}},
                           {"languages": {"en": "Gaes", "ru":"Гаэс"}},
                           {"languages": {"en": "Ged", "ru":"Гед"}},
                           {"languages": {"en": "Gen", "ru":"Ген"}},
                           {"languages": {"en": "Ges", "ru":"Гес"}},
                           {"languages": {"en": "Geth", "ru":"Гет"}},
                           {"languages": {"en": "Glor", "ru":"Глор"}},
                           {"languages": {"en": "Has", "ru":"Хас"}},
                           {"languages": {"en": "Hath", "ru":"Хат"}},
                           {"languages": {"en": "Hel", "ru":"Хэль"}},
                           {"languages": {"en": "Heth", "ru":"Хет"}},
                           {"languages": {"en": "Hith", "ru":"Хит"}},
                           {"languages": {"en": "Ill", "ru":"Илл"}},
                           {"languages": {"en": "Ind", "ru":"Инд"}},
                           {"languages": {"en": "Ist", "ru":"Ист"}},
                           {"languages": {"en": "Ith", "ru":"Ит"}},
                           {"languages": {"en": "Iy", "ru":"Ай"}},
                           {"languages": {"en": "Kor", "ru":"Кор"}},
                           {"languages": {"en": "Ky", "ru":"Кай"}},
                           {"languages": {"en": "Kyr", "ru":"Кайр"}},
                           {"languages": {"en": "La", "ru":"Ла"}},
                           {"languages": {"en": "Lan", "ru":"Лан"}},
                           {"languages": {"en": "Lil", "ru":"Лил"}},
                           {"languages": {"en": "Lim", "ru":"Лим"}},
                           {"languages": {"en": "Lith", "ru":"Лит"}},
                           {"languages": {"en": "Loth", "ru":"Лот"}},
                           {"languages": {"en": "Mal", "ru":"Мэл"}},
                           {"languages": {"en": "Mar", "ru":"Мар"}},
                           {"languages": {"en": "Mas", "ru":"Мас"}},
                           {"languages": {"en": "Math", "ru":"Мат"}},
                           {"languages": {"en": "Me", "ru":"Ме"}},
                           {"languages": {"en": "Mes", "ru":"Мес"}},
                           {"languages": {"en": "Meth", "ru":"Мет"}},
                           {"languages": {"en": "Men", "ru":"Мен"}},
                           {"languages": {"en": "Mor", "ru":"Мор"}},
                           {"languages": {"en": "Mort", "ru":"Морт"}},
                           {"languages": {"en": "Nal", "ru":"Нал"}},
                           {"languages": {"en": "Nar", "ru":"Нар"}},
                           {"languages": {"en": "Nen", "ru":"Нен"}},
                           {"languages": {"en": "Nor", "ru":"Нор"}},
                           {"languages": {"en": "Norl", "ru":"Норль"}},
                           {"languages": {"en": "Ri", "ru":"Ри"}},
                           {"languages": {"en": "Riabb", "ru":"Риабб"}},
                           {"languages": {"en": "Riann", "ru":"Рианн"}},
                           {"languages": {"en": "Rid", "ru":"Рид"}},
                           {"languages": {"en": "Riell", "ru":"Риэлль"}},
                           {"languages": {"en": "Rien", "ru":"Риэн"}},
                           {"languages": {"en": "Ruth", "ru":"Рут"}},
                           {"languages": {"en": "Ryn", "ru":"Райн"}},
                           {"languages": {"en": "Tab", "ru":"Таб"}},
                           {"languages": {"en": "Tal", "ru":"Тал"}},
                           {"languages": {"en": "Tan", "ru":"Тан"}},
                           {"languages": {"en": "Tar", "ru":"Тар"}},
                           {"languages": {"en": "Teth", "ru":"Тет"}},
                           {"languages": {"en": "Tel", "ru":"Тэл"}},
                           {"languages": {"en": "Tor", "ru":"Тор"}},
                           {"languages": {"en": "Ty", "ru":"Тай"}},
                           {"languages": {"en": "Ul", "ru":"Уль"}},
                           {"languages": {"en": "Um", "ru":"Ум"}},
                           {"languages": {"en": "Ur", "ru":"Ур"}},
                           {"languages": {"en": "Yr", "ru":"Айр"}},
                           {"languages": {"en": "Yv", "ru":"Ии"}}],

                "connection": [{"languages": {"en": "a", "ru":"а"}},
                               {"languages": {"en": "al", "ru":"аль"}},
                               {"languages": {"en": "an", "ru":"ан"}},
                               {"languages": {"en": "ar", "ru":"ар"}},
                               {"languages": {"en": "as", "ru":"ас"}},
                               {"languages": {"en": "e", "ru":"э"}},
                               {"languages": {"en": "el", "ru":"эль"}},
                               {"languages": {"en": "en", "ru":"эн"}},
                               {"languages": {"en": "er", "ru":"ер"}},
                               {"languages": {"en": "es", "ru":"ес"}},
                               {"languages": {"en": "fan", "ru":"фан"}},
                               {"languages": {"en": "fen", "ru":"фен"}},
                               {"languages": {"en": "fin", "ru":"фин"}},
                               {"languages": {"en": "i", "ru":"и"}},
                               {"languages": {"en": "il", "ru":"иль"}},
                               {"languages": {"en": "in", "ru":"ин"}},
                               {"languages": {"en": "ir", "ru":"ир"}},
                               {"languages": {"en": "is", "ru":"ис"}},
                               {"languages": {"en": "o", "ru":"о"}},
                               {"languages": {"en": "ol", "ru":"ол"}},
                               {"languages": {"en": "on", "ru":"он"}},
                               {"languages": {"en": "or", "ru":"ор"}},
                               {"languages": {"en": "os", "ru":"ос"}},
                               {"languages": {"en": "ra", "ru":"ра"}},
                               {"languages": {"en": "ral", "ru":"рал"}},
                               {"languages": {"en": "ran", "ru":"ран"}},
                               {"languages": {"en": "re", "ru":"ре"}},
                               {"languages": {"en": "rel", "ru":"рел"}},
                               {"languages": {"en": "ren", "ru":"рен"}},
                               {"languages": {"en": "ri", "ru":"ри"}},
                               {"languages": {"en": "ril", "ru":"рил"}},
                               {"languages": {"en": "rin", "ru":"рин"}},
                               {"languages": {"en": "ro", "ru":"ро"}},
                               {"languages": {"en": "rol", "ru":"рол"}},
                               {"languages": {"en": "ron", "ru":"рон"}},
                               {"languages": {"en": "ry", "ru":"рай"}},
                               {"languages": {"en": "sa", "ru":"са"}},
                               {"languages": {"en": "sal", "ru":"сал"}},
                               {"languages": {"en": "san", "ru":"сан"}},
                               {"languages": {"en": "se", "ru":"се"}},
                               {"languages": {"en": "sel", "ru":"сел"}},
                               {"languages": {"en": "sen", "ru":"сен"}},
                               {"languages": {"en": "si", "ru":"си"}},
                               {"languages": {"en": "sil", "ru":"сил"}},
                               {"languages": {"en": "sin", "ru":"син"}},
                               {"languages": {"en": "so", "ru":"со"}},
                               {"languages": {"en": "sol", "ru":"сол"}},
                               {"languages": {"en": "son", "ru":"сон"}},
                               {"languages": {"en": "u", "ru":"у"}},
                               {"languages": {"en": "ul", "ru":"ул"}}],

                "male_suffix": [{"languages": {"en": "baen", "ru":"баэн"}},
                                {"languages": {"en": "baine", "ru":"бэйн"}},
                                {"languages": {"en": "baire", "ru":"бэйр"}},
                                {"languages": {"en": "bar", "ru":"бар"}},
                                {"languages": {"en": "bhir", "ru":"бир"}},
                                {"languages": {"en": "brier", "ru":"брир"}},
                                {"languages": {"en": "brior", "ru":"бриор"}},
                                {"languages": {"en": "brin", "ru":"брин"}},
                                {"languages": {"en": "daen", "ru":"даэн"}},
                                {"languages": {"en": "daine", "ru":"дэйн"}},
                                {"languages": {"en": "daire", "ru":"дэйр"}},
                                {"languages": {"en": "dar", "ru":"дар"}},
                                {"languages": {"en": "dhil", "ru":"дил"}},
                                {"languages": {"en": "dhir", "ru":"дир"}},
                                {"languages": {"en": "drel", "ru":"дрел"}},
                                {"languages": {"en": "drir", "ru":"дрир"}},
                                {"languages": {"en": "dror", "ru":"дрор"}},
                                {"languages": {"en": "eorl", "ru":"эорл"}},
                                {"languages": {"en": "eos", "ru":"эос"}},
                                {"languages": {"en": "eoth", "ru":"эот"}},
                                {"languages": {"en": "fil", "ru":"фил"}},
                                {"languages": {"en": "fin", "ru":"фин"}},
                                {"languages": {"en": "fir", "ru":"фир"}},
                                {"languages": {"en": "hil", "ru":"хил"}},
                                {"languages": {"en": "hin", "ru":"хин"}},
                                {"languages": {"en": "hir", "ru":"хир"}},
                                {"languages": {"en": "hor", "ru":"хор"}},
                                {"languages": {"en": "il", "ru":"ил"}},
                                {"languages": {"en": "in", "ru":"ин"}},
                                {"languages": {"en": "ion", "ru":"ион"}},
                                {"languages": {"en": "ir", "ru":"ир"}},
                                {"languages": {"en": "is", "ru":"ис"}},
                                {"languages": {"en": "ith", "ru":"ит"}},
                                {"languages": {"en": "lael", "ru":"лаэл"}},
                                {"languages": {"en": "laern", "ru":"лаэрн"}},
                                {"languages": {"en": "laer", "ru":"лаэр"}},
                                {"languages": {"en": "laine", "ru":"лэйн"}},
                                {"languages": {"en": "laire", "ru":"лэйр"}},
                                {"languages": {"en": "lan", "ru":"лан"}},
                                {"languages": {"en": "las", "ru":"лас"}},
                                {"languages": {"en": "len", "ru":"лен"}},
                                {"languages": {"en": "les", "ru":"лес"}},
                                {"languages": {"en": "lil", "ru":"лил"}},
                                {"languages": {"en": "lin", "ru":"лин"}},
                                {"languages": {"en": "lir", "ru":"лир"}},
                                {"languages": {"en": "lis", "ru":"лис"}},
                                {"languages": {"en": "lor", "ru":"лор"}},
                                {"languages": {"en": "los", "ru":"лос"}},
                                {"languages": {"en": "mael", "ru":"маэл"}},
                                {"languages": {"en": "maen", "ru":"маэн"}},
                                {"languages": {"en": "mair", "ru":"мэйр"}},
                                {"languages": {"en": "main", "ru":"мэйн"}},
                                {"languages": {"en": "mal", "ru":"мал"}},
                                {"languages": {"en": "mar", "ru":"мар"}},
                                {"languages": {"en": "mil", "ru":"мил"}},
                                {"languages": {"en": "min", "ru":"мин"}},
                                {"languages": {"en": "mir", "ru":"мир"}},
                                {"languages": {"en": "nael", "ru":"наэл"}},
                                {"languages": {"en": "naen", "ru":"наэн"}},
                                {"languages": {"en": "naer", "ru":"наэр"}},
                                {"languages": {"en": "nail", "ru":"нэйл"}},
                                {"languages": {"en": "nair", "ru":"нэйр"}},
                                {"languages": {"en": "nal", "ru":"нал"}},
                                {"languages": {"en": "nan", "ru":"нан"}},
                                {"languages": {"en": "nar", "ru":"нар"}},
                                {"languages": {"en": "neal", "ru":"неал"}},
                                {"languages": {"en": "nean", "ru":"неан"}},
                                {"languages": {"en": "near", "ru":"неар"}},
                                {"languages": {"en": "nil", "ru":"нил"}},
                                {"languages": {"en": "nin", "ru":"нин"}},
                                {"languages": {"en": "nir", "ru":"нир"}},
                                {"languages": {"en": "nis", "ru":"нис"}},
                                {"languages": {"en": "ran", "ru":"ран"}},
                                {"languages": {"en": "rea", "ru":"рэа"}},
                                {"languages": {"en": "rel", "ru":"рел"}},
                                {"languages": {"en": "ril", "ru":"рил"}},
                                {"languages": {"en": "riol", "ru":"риол"}},
                                {"languages": {"en": "rion", "ru":"рион"}},
                                {"languages": {"en": "rior", "ru":"риор"}},
                                {"languages": {"en": "riorl", "ru":"риорл"}},
                                {"languages": {"en": "riorn", "ru":"риорн"}},
                                {"languages": {"en": "rir", "ru":"рир"}},
                                {"languages": {"en": "ryel", "ru":"райэл"}},
                                {"languages": {"en": "taen", "ru":"таэн"}},
                                {"languages": {"en": "tair", "ru":"тэйр"}},
                                {"languages": {"en": "tain", "ru":"тэйн"}},
                                {"languages": {"en": "than", "ru":"тан"}},
                                {"languages": {"en": "thar", "ru":"тар"}},
                                {"languages": {"en": "thel", "ru":"тел"}},
                                {"languages": {"en": "thil", "ru":"ттил"}},
                                {"languages": {"en": "thir", "ru":"тир"}},
                                {"languages": {"en": "thin", "ru":"ттин"}},
                                {"languages": {"en": "thril", "ru":"трил"}},
                                {"languages": {"en": "thrin", "ru":"трин"}},
                                {"languages": {"en": "thwe", "ru":"тве"}},
                                {"languages": {"en": "til", "ru":"тил"}},
                                {"languages": {"en": "tin", "ru":"тин"}},
                                {"languages": {"en": "tis", "ru":"тис"}},
                                {"languages": {"en": "we", "ru":"ве"}},
                                {"languages": {"en": "yan", "ru":"ян"}}],
                
                "female_suffix": [{"languages": {"en": "a", "ru":"а"}},
                                  {"languages": {"en": "aine", "ru":"айн"}},
                                  {"languages": {"en": "am", "ru":"ам"}},
                                  {"languages": {"en": "ann", "ru":"анн"}},
                                  {"languages": {"en": "arma", "ru":"арма"}},
                                  {"languages": {"en": "arna", "ru":"арна"}},
                                  {"languages": {"en": "arth", "ru":"арт"}},
                                  {"languages": {"en": "ath", "ru":"ат"}},
                                  {"languages": {"en": "beann", "ru":"биэнн"}},
                                  {"languages": {"en": "bet", "ru":"бет"}},
                                  {"languages": {"en": "beth", "ru":"бэт"}},
                                  {"languages": {"en": "brim", "ru":"брим"}},
                                  {"languages": {"en": "brys", "ru":"брайс"}},
                                  {"languages": {"en": "deann", "ru":"деанн"}},
                                  {"languages": {"en": "det", "ru":"дет"}},
                                  {"languages": {"en": "deth", "ru":"детт"}},
                                  {"languages": {"en": "dys", "ru":"дайс"}},
                                  {"languages": {"en": "drian", "ru":"дриан"}},
                                  {"languages": {"en": "driel", "ru":"дриэль"}},
                                  {"languages": {"en": "drys", "ru":"драйс"}},
                                  {"languages": {"en": "eann", "ru":"иэнн"}},
                                  {"languages": {"en": "eanna", "ru":"ианна"}},
                                  {"languages": {"en": "earna", "ru":"иарна"}},
                                  {"languages": {"en": "earth", "ru":"иарт"}},
                                  {"languages": {"en": "elle", "ru":"элле"}},
                                  {"languages": {"en": "eth", "ru":"ет"}},
                                  {"languages": {"en": "eys", "ru":"айс"}},
                                  {"languages": {"en": "eyth", "ru":"айт"}},
                                  {"languages": {"en": "felle", "ru":"фэлль"}},
                                  {"languages": {"en": "fionn", "ru":"фионн"}},
                                  {"languages": {"en": "flys", "ru":"флайс"}},
                                  {"languages": {"en": "fyll", "ru":"филль"}},
                                  {"languages": {"en": "fynn", "ru":"финн"}},
                                  {"languages": {"en": "fyr", "ru":"файр"}},
                                  {"languages": {"en": "fys", "ru":"файс"}},
                                  {"languages": {"en": "i", "ru":"и"}},
                                  {"languages": {"en": "ille", "ru":"илль"}},
                                  {"languages": {"en": "ina", "ru":"ина"}},
                                  {"languages": {"en": "ira", "ru":"ира"}},
                                  {"languages": {"en": "isa", "ru":"иса"}},
                                  {"languages": {"en": "ithi", "ru":"ити"}},
                                  {"languages": {"en": "itt", "ru":"итт"}},
                                  {"languages": {"en": "la", "ru":"ла"}},
                                  {"languages": {"en": "lam", "ru":"лам"}},
                                  {"languages": {"en": "lana", "ru":"лана"}},
                                  {"languages": {"en": "larna", "ru":"ларна"}},
                                  {"languages": {"en": "lath", "ru":"лат"}},
                                  {"languages": {"en": "leann", "ru":"лиэнн"}},
                                  {"languages": {"en": "leath", "ru":"лиат"}},
                                  {"languages": {"en": "lel", "ru":"лель"}},
                                  {"languages": {"en": "lelle", "ru":"лелль"}},
                                  {"languages": {"en": "leth", "ru":"лет"}},
                                  {"languages": {"en": "let", "ru":"лет"}},
                                  {"languages": {"en": "lielle", "ru":"лиэлль"}},
                                  {"languages": {"en": "lieth", "ru":"лайет"}},
                                  {"languages": {"en": "lyann", "ru":"лайенн"}},
                                  {"languages": {"en": "nelle", "ru":"нэлль"}},
                                  {"languages": {"en": "nem", "ru":"нем"}},
                                  {"languages": {"en": "neth", "ru":"нет"}},
                                  {"languages": {"en": "ni", "ru":"ни"}},
                                  {"languages": {"en": "nielle", "ru":"ниэлль"}},
                                  {"languages": {"en": "niella", "ru":"ниэлла"}},
                                  {"languages": {"en": "nith", "ru":"нит"}},
                                  {"languages": {"en": "ras", "ru":"рас"}},
                                  {"languages": {"en": "reann", "ru":"риэнн"}},
                                  {"languages": {"en": "rell", "ru":"рэлль"}},
                                  {"languages": {"en": "relle", "ru":"рэлли"}},
                                  {"languages": {"en": "rielle", "ru":"риэлль"}},
                                  {"languages": {"en": "ris", "ru":"рис"}},
                                  {"languages": {"en": "rith", "ru":"рит"}},
                                  {"languages": {"en": "rys", "ru":"райс"}},
                                  {"languages": {"en": "sar", "ru":"сар"}},
                                  {"languages": {"en": "sath", "ru":"сат"}},
                                  {"languages": {"en": "ser", "ru":"сер"}},
                                  {"languages": {"en": "seth", "ru":"сет"}},
                                  {"languages": {"en": "sir", "ru":"сир"}},
                                  {"languages": {"en": "sith", "ru":"сит"}},
                                  {"languages": {"en": "sor", "ru":"сор"}},
                                  {"languages": {"en": "soth", "ru":"сот"}},
                                  {"languages": {"en": "shar", "ru":"шар"}},
                                  {"languages": {"en": "sher", "ru":"шер"}},
                                  {"languages": {"en": "shir", "ru":"шир"}},
                                  {"languages": {"en": "sys", "ru":"сис"}},
                                  {"languages": {"en": "tar", "ru":"тар"}},
                                  {"languages": {"en": "teal", "ru":"тиль"}},
                                  {"languages": {"en": "teann", "ru":"тиэнн"}},
                                  {"languages": {"en": "ter", "ru":"тер"}},
                                  {"languages": {"en": "thea", "ru":"тэа"}},
                                  {"languages": {"en": "ther", "ru":"тер"}},
                                  {"languages": {"en": "thi", "ru":"ти"}},
                                  {"languages": {"en": "thryn", "ru":"трин"}},
                                  {"languages": {"en": "tir", "ru":"тир"}},
                                  {"languages": {"en": "tor", "ru":"тор"}},
                                  {"languages": {"en": "tos", "ru":"тос"}},
                                  {"languages": {"en": "tryan", "ru":"триан"}},
                                  {"languages": {"en": "trys", "ru":"трис"}},
                                  {"languages": {"en": "yll", "ru":"илль"}},
                                  {"languages": {"en": "yrs", "ru":"ирс"}},
                                  {"languages": {"en": "ys", "ru":"ис"}}] }
}
